telegram_parser/__init__.py
telegram_parser/__main__.py
telegram_parser/cli.py
telegram_parser-0.0.1.dist-info/entry_points.txt
telegram_parser-0.0.1.dist-info/WHEEL
telegram_parser-0.0.1.dist-info/METADATA
telegram_parser-0.0.1.dist-info/RECORD
